mercuryV1/__init__.py
mercuryV1/addresses.py
mercuryV1/assets.py
mercuryV1/base.py
mercuryV1/contactMethods.py
mercuryV1/contacts.py
mercuryV1/expenses.py
mercuryV1/incomes.py
mercuryV1/liabilities.py
mercuryV1/mercury.py
mercuryV1/nestedBase.py
mercuryV1/opportunities.py
mercuryV1/relatedParties.py
mercuryV1-0.1.data/scripts/mercury
mercuryV1-0.1.dist-info/LICENSE
mercuryV1-0.1.dist-info/METADATA
mercuryV1-0.1.dist-info/WHEEL
mercuryV1-0.1.dist-info/top_level.txt
mercuryV1-0.1.dist-info/RECORD
