Metadata-Version: 2.1
Name: mercuryV1
Version: 0.1
Summary: API wrapper library in python for mercury CRM
Home-page: https://github.com/kierenfunk/mercuryV1/
Author: Kieren Funk
Author-email: kierenfunk@gmail.com
License: UNKNOWN
Platform: UNKNOWN
Classifier: Programming Language :: Python :: 3
Classifier: License :: OSI Approved :: MIT License
Classifier: Operating System :: OS Independent
